cjm_fasthtml_app_core/__init__.py
cjm_fasthtml_app_core/_modidx.py
cjm_fasthtml_app_core/components/__init__.py
cjm_fasthtml_app_core/components/alerts.py
cjm_fasthtml_app_core/components/navbar.py
cjm_fasthtml_app_core/core/__init__.py
cjm_fasthtml_app_core/core/html_ids.py
cjm_fasthtml_app_core/core/htmx.py
cjm_fasthtml_app_core/core/layout.py
cjm_fasthtml_app_core-0.0.2.dist-info/licenses/LICENSE
cjm_fasthtml_app_core-0.0.2.dist-info/METADATA
cjm_fasthtml_app_core-0.0.2.dist-info/WHEEL
cjm_fasthtml_app_core-0.0.2.dist-info/entry_points.txt
cjm_fasthtml_app_core-0.0.2.dist-info/top_level.txt
cjm_fasthtml_app_core-0.0.2.dist-info/RECORD
